datatrack/__init__.py
datatrack/cli.py
datatrack/connect.py
datatrack/diff.py
datatrack/exporter.py
datatrack/history.py
datatrack/linter.py
datatrack/pipeline.py
datatrack/test_connection.py
datatrack/tracker.py
datatrack/verifier.py
datatrack_core-1.1.8.dist-info/licenses/LICENSE
datatrack_core-1.1.8.dist-info/METADATA
datatrack_core-1.1.8.dist-info/WHEEL
datatrack_core-1.1.8.dist-info/entry_points.txt
datatrack_core-1.1.8.dist-info/top_level.txt
datatrack_core-1.1.8.dist-info/RECORD
